MSPT/TrianglePascal.py
MSPT/__init__.py
MSPT/notebook.py
MSPT-1.1.0.dist-info/LICENSE.txt
MSPT-1.1.0.dist-info/METADATA
MSPT-1.1.0.dist-info/WHEEL
MSPT-1.1.0.dist-info/top_level.txt
MSPT-1.1.0.dist-info/RECORD
